Tornado_JSON-1.3.4.dist-info/METADATA
Tornado_JSON-1.3.4.dist-info/RECORD
Tornado_JSON-1.3.4.dist-info/WHEEL
Tornado_JSON-1.3.4.dist-info/top_level.txt
tornado_json/__init__.py
tornado_json/api_doc_gen.py
tornado_json/application.py
tornado_json/constants.py
tornado_json/exceptions.py
tornado_json/gen.py
tornado_json/jsend.py
tornado_json/requesthandlers.py
tornado_json/response.py
tornado_json/routes.py
tornado_json/schema.py
tornado_json/utils.py
