Metadata-Version: 2.1
Name: Tornado-JSON
Version: 1.3.4
Summary: A simple JSON API framework based on Tornado
Home-page: https://github.com/hfaran/Tornado-JSON
Author: Hamza Faran
Author-email: UNKNOWN
License: MIT License
Platform: UNKNOWN
Classifier: Development Status :: 5 - Production/Stable
Classifier: Intended Audience :: Developers
Classifier: License :: OSI Approved :: MIT License
Classifier: Natural Language :: English
Classifier: Operating System :: OS Independent
Classifier: Programming Language :: Python :: 2.7
Classifier: Programming Language :: Python :: 3.6
Classifier: Topic :: Software Development :: Libraries :: Application Frameworks
Requires-Dist: tornado (<6.0,>=3.2.2)
Requires-Dist: jsonschema (<3.0,>=2.3.0)
